ruleex/__init__.py
ruleex/anndt/__init__.py
ruleex/anndt/core.py
ruleex/anndt/measures.py
ruleex/anndt/sampling.py
ruleex/anndt/stat_test.py
ruleex/deepred/__init__.py
ruleex/deepred/core.py
ruleex/deepred/model.py
ruleex/hypinv/__init__.py
ruleex/hypinv/core.py
ruleex/hypinv/data.py
ruleex/hypinv/model.py
ruleex/tree/__init__.py
ruleex/tree/build.py
ruleex/tree/oblique.py
ruleex/tree/rule.py
ruleex/tree/ruletree.py
ruleex/tree/rutils.py
ruleex/tree/utils.py
ruleex-0.4.1.dist-info/METADATA
ruleex-0.4.1.dist-info/RECORD
ruleex-0.4.1.dist-info/WHEEL
ruleex-0.4.1.dist-info/top_level.txt
