Metadata-Version: 2.1
Name: ruleex
Version: 0.4.1
Summary: Rule extraction methods from neural networks
Home-page: https://github.com/fantamat/ruleex
Author: Matěj Fanta
Author-email: fantamat93@gmail.com
License: MIT
Platform: UNKNOWN
Classifier: Programming Language :: Python :: 3
Classifier: License :: OSI Approved :: MIT License
Classifier: Operating System :: OS Independent
Classifier: Topic :: Software Development :: Libraries :: Python Modules
Classifier: Topic :: Scientific/Engineering
